backend/__init__.py
backend/backend_ibm.py
benchmarking/__init__.py
calibration/__init__.py
calibration/discriminator.py
calibration/drag.py
calibration/fine_tune.py
calibration/rough_rabi.py
calibration/transmission_reflection.py
calibration/utility.py
characterization/__init__.py
clifford/__init__.py
decomposition/__init__.py
decomposition/transpilation.py
exceptions/__init__.py
exceptions/pulse_exception.py
quantumcircuit/QC.py
quantumcircuit/__init__.py
quantumcircuit/instruction_structure.py
quantumcircuit/qc_elementary_matrices.py
quantumcircuit/qc_utility.py
tomography/Qutrit_tomo.py
tomography/__init__.py
vm_backend/QASM_backend.py
vm_backend/__init__.py
qutritium-0.0.1.dist-info/LICENSE.txt
qutritium-0.0.1.dist-info/METADATA
qutritium-0.0.1.dist-info/WHEEL
qutritium-0.0.1.dist-info/top_level.txt
qutritium-0.0.1.dist-info/RECORD
