Metadata-Version: 2.1
Name: qutritium
Version: 0.0.1
Summary: Qutritium package provides basic calibration and features for qutrit system using Qiskit and other quantum packages
Home-page: https://github.com/spham1611/qutritium
Author: Son Pham, Tien Nguyen, Bao Bach
Author-email: reachphamhson@gmail.com
License: MIT License
Project-URL: Bug Tracker, https://github.com/spham1611/qutritium/~/issues
Project-URL: repository, https://github.com/spham1611/qutritium
Classifier: Programming Language :: Python :: 3
Classifier: License :: OSI Approved :: MIT License
Classifier: Operating System :: OS Independent
Classifier: Topic :: Utilities
Requires-Python: >=3.6
License-File: LICENSE.txt
